rename_ts_folder/__init__.py
rename_ts_folder/app.py
rename_ts_folder/rename_folder.py
tests/__init__.py
tests/clean_up.py
tests/conftest.py
tests/run_test.py
tests/setup_tests.py
tests/test_1.py
tests/test_2.py
rename_ts_folder-0.2.1.dist-info/LICENSE
rename_ts_folder-0.2.1.dist-info/METADATA
rename_ts_folder-0.2.1.dist-info/WHEEL
rename_ts_folder-0.2.1.dist-info/entry_points.txt
rename_ts_folder-0.2.1.dist-info/top_level.txt
rename_ts_folder-0.2.1.dist-info/RECORD
