Metadata-Version: 2.1
Name: rename-ts-folder
Version: 0.2.1
Summary: Rename a folder based on the numbering of a file's name inside that folder
Home-page: UNKNOWN
Author: Yuhang (Steven) Wang
Author-email: UNKNOWN
License: UNKNOWN
Platform: UNKNOWN
